{
  "$schema": "../../../../schemas/faq-entries.schema.json",
  "entries": [
    {
      "question": "内科の訪問診療はどんな病気に対応していますか？",
      "answerPlain": "高血圧・糖尿病・心不全・慢性腎臓病・COPD・がんなど慢性疾患の継続管理が中心です。定期的な診察・採血・処方のほか、点滴・創傷処置・在宅酸素の管理なども行います。病状が安定している方も、進行した状態の方も対応しています。",
      "trailingSnippet": "phoneFormConsult"
    },
    {
      "question": "採血や検査は自宅でできますか？",
      "answerPlain": "はい。訪問時に採血・尿検査・心電図など基本的な検査を実施できます。検査結果は次回訪問時または電話でご説明します。精密検査が必要な場合は、連携医療機関への紹介も行います。"
    },
    {
      "question": "末期がんの緩和ケアも対応できますか？",
      "answerPlain": "はい。がんの末期・ターミナル期の在宅緩和ケアに対応しています。痛みのコントロール（医療用麻薬の管理含む）、倦怠感・呼吸困難への対処、ご家族への精神的サポートまで行います。かもめクリニックはグループ全体で年間約100件の在宅看取り実績があります。"
    },
    {
      "question": "複数の慢性疾患があっても対応できますか？",
      "answerPlain": "はい。高血圧・糖尿病・慢性腎臓病など複数の疾患を抱える方の「かかりつけ医」として、総合的に管理します。専門科が必要な場合は院内の精神科・小児科専門医と連携し、外部の病院への紹介も行います。"
    },
    {
      "question": "訪問診療の費用はどのくらいかかりますか？",
      "answerPlain": "健康保険・介護保険が適用されます。後期高齢者（75歳以上・1割負担）は月2回の定期訪問で月額5,000〜8,000円が目安（薬代・処置費用は別途）。生活保護の方は自己負担ゼロです。",
      "trailingSnippet": "costPageAndPhone"
    }
  ]
}
